apollo11log/__main__.py
apollo11log/log.txt
apollo11log-0.1.3.dist-info/entry_points.txt
apollo11log-0.1.3.dist-info/WHEEL
apollo11log-0.1.3.dist-info/METADATA
apollo11log-0.1.3.dist-info/RECORD
